{
  "source": {
    "name": "Slashdot",
    "url": "https://www.slashdot.org",
    "language": "English",
    "group": "News & Blogs/English"
  },
  "requested_url": "https://www.slashdot.org",
  "final_url": "https://slashdot.org/",
  "status_code": 200,
  "fetched_at": "2025-09-13T11:20:03.435292Z",
  "headers": {
    "Date": "Sat, 13 Sep 2025 11:20:11 GMT",
    "Content-Type": "text/html; charset=utf-8",
    "Transfer-Encoding": "chunked",
    "Connection": "keep-alive",
    "Content-Encoding": "gzip",
    "CF-Ray": "97e741000ecad77e-LHR",
    "CF-Cache-Status": "DYNAMIC",
    "Cache-Control": "no-cache",
    "Strict-Transport-Security": "max-age=31536000",
    "Pragma": "no-cache",
    "content-security-policy": "frame-ancestors 'self'; upgrade-insecure-requests;form-action 'self' slashdot.org slashdot.us15.list-manage.com;fenced-frame-src https:; frame-src 'self' slashdot.org *.lijit.com btloader.com *.btloader.com *.btmessage.com http://*.pro-market.net *.crsspxl.com *.google.com *.googlesyndication.com *.safeframe.usercontent.goog *.doubleclick.net *.gstatic.com *.googleadservices.com *.adtrafficquality.google console.googletagservices.com *.amazon-adsystem.com challenges.cloudflare.com *.adnxs.com *.indexww.com *.rubiconproject.com *.pubmatic.com *.smartadserver.com *.tapad.com http://*.youtube.com http://*.youtube-nocookie.com slashdotmedia.com as.slashdot.org *.as.slashdot.org error-report.com *.error-report.com html-load.com *.html-load.com *.fb.html-load.com content-loader.com *.content-loader.com *.fb.content-loader.com css-load.com *.css-load.com 07c225f3.online *.07c225f3.online *.criteo.com *.openx.net *.pghub.io; object-src http://*.youtube.com;script-src 'self' slashdot.org *.slashdot.org slashdot.org *.slashdotmedia.com a.fsdn.com challenges.cloudflare.com *.lijit.com *.moatads.com *.adsafeprotected.com *.sharethrough.com *.2mdn.net *.adnxs.com *.bing.com *.script.ac *.ybp.yahoo.com *.adnxs-simple.com *.truste.com *.adrta.com pghub.io/js/pandg-sdk.js *.pubmatic.com ml314.com *.stack-sonar.com *.licdn.com translate.googleapis.com *.doubleclick.net *.googleadservices.com *.adtrafficquality.google translate.google.cn *.gstatic.cn *.google.com *.ampproject.org *.amazon-adsystem.com *.criteo.net *.creativecdn.com *.crwdcntrl.net *.uidapi.com *.im-apps.net *.euid.eu *.openxcdn.net *.id5-sync.com cdn.jsdelivr.net/gh/prebid/shared-id/ *.33across.com *.consentmanager.net *.microsofttranslator.com *.gstatic.com *.googletagservices.com *.google-analytics.com *.googlesyndication.com *.cloudflareinsights.com d3tglifpd8whs6.cloudfront.net rpxnow.com btloader.com *.btmessage.com *.crsspxl.com http://*.pro-market.net *.4dex.io *.adnxs-simple.com *.s-onetag.com *.rubiconproject.com *.trustarc.com *.truste.com *.doubleverify.com *.tapad.com *.pghub.io pghub.io *.sharethru.com j.6sc.co as.slashdot.org *.as.slashdot.org html-load.com *.html-load.com *.fb.html-load.com content-loader.com *.content-loader.com *.fb.content-loader.com css-load.com *.css-load.com 07c225f3.online *.07c225f3.online cmp.inmobi.com *.inmobicdn.net blob: adservice.google.ad adservice.google.ae adservice.google.at adservice.google.be adservice.google.bg adservice.google.ca adservice.google.ch adservice.google.co.id adservice.google.co.il adservice.google.co.in adservice.google.co.jp adservice.google.co.kr adservice.google.co.th adservice.google.co.uk adservice.google.co.zw adservice.google.com.au adservice.google.com.bo adservice.google.com.hk adservice.google.com.mx adservice.google.com.ph adservice.google.com.pk adservice.google.com.sa adservice.google.com.sg adservice.google.com.tr adservice.google.com.tw adservice.google.com.ua adservice.google.com.vn adservice.google.cz adservice.google.de adservice.google.dk adservice.google.dz adservice.google.ee adservice.google.fi adservice.google.fr adservice.google.gr adservice.google.hu adservice.google.ie adservice.google.it adservice.google.li adservice.google.lu adservice.google.mu adservice.google.mv adservice.google.nl adservice.google.no adservice.google.pl adservice.google.pt adservice.google.ro adservice.google.rs adservice.google.se adservice.google.sk adservice.google.com.br adservice.google.com.ar adservice.google.cl adservice.google.com.co adservice.google.com.cu adservice.google.com.cy adservice.google.es adservice.google.hr adservice.google.im adservice.google.lk adservice.google.me adservice.google.mg adservice.google.com.mm adservice.google.com.ng adservice.google.com.np adservice.google.com.pr adservice.google.com.uy adservice.google.co.za adservice.google.jo adservice.google.bs adservice.google.al adservice.google.co.tz adservice.google.rw adservice.google.hn adservice.google.lt adservice.google.iq adservice.google.si adservice.google.bj adservice.google.co.ao adservice.google.com.gh adservice.google.kz adservice.google.com.eg adservice.google.com.ec adservice.google.co.ve adservice.google.com.py adservice.google.lv adservice.google.mn adservice.google.com.bn adservice.google.tn adservice.google.ml adservice.google.is adservice.google.com.sv adservice.google.com.bz adservice.google.az adservice.google.gt adservice.google.sn adservice.google.cm adservice.google.com.kh adservice.google.ge adservice.google.com.et adservice.google.com.pe adservice.google.com.ly adservice.google.co.mz adservice.google.com.bh adservice.google.com.mt adservice.google.ps adservice.google.so adservice.google.bf adservice.google.co.nz adservice.google.com.gt adservice.google.co.zm adservice.google.je adservice.google.cv adservice.google.la adservice.google.bi adservice.google.com.jm adservice.google.tt adservice.google.com.kw adservice.google.cd adservice.google.gy adservice.google.tg adservice.google.com.af adservice.google.com.lb adservice.google.sr adservice.google.com.ni adservice.google.ki adservice.google.com.na adservice.google.ht adservice.google.nr adservice.google.td adservice.google.co.ls adservice.google.gl adservice.google.bt adservice.google.tm adservice.google.com.vc adservice.google.co.bw adservice.google.vg adservice.google.as adservice.google.cg adservice.google.com.ag adservice.google.com.tj adservice.google.dm adservice.google.to adservice.google.dj adservice.google.cf adservice.google.ws adservice.google.st adservice.google.gm adservice.google.fm adservice.google.com.sb adservice.google.com.pg adservice.google.com.gi adservice.google.com.ai adservice.google.co.ck adservice.google.ru adservice.google.nu adservice.google.com.my adservice.google.com.bd adservice.google.ci adservice.google.co.cr adservice.google.co.ke adservice.google.co.ug adservice.google.co.uz adservice.google.co.vi adservice.google.ms adservice.google.com.fj adservice.google.com.om adservice.google.com.pa adservice.google.com.qa adservice.google.ga adservice.google.gg adservice.google.kg adservice.google.md adservice.google.mk adservice.google.mw adservice.google.ne adservice.google.sm adservice.google.tl adservice.google.sc adservice.google.vu 'unsafe-inline' 'unsafe-eval';",
    "cross-origin-opener-policy": "same-origin",
    "feature-policy": "geolocation 'none'; microphone 'none'; camera 'none'; payment 'none'; document-domain 'none'; display-capture 'none'; autoplay 'none'",
    "permissions-policy": "geolocation=(), microphone=(), camera=(), payment=(), document-domain=(), display-capture=(), autoplay=()",
    "slash_log_data": "shtml",
    "x-frame-options": "SAMEORIGIN",
    "x-xrds-location": "https://slashdot.org/slashdot.xrds",
    "Vary": "Accept-Encoding",
    "Server": "cloudflare",
    "alt-svc": "h3=\":443\"; ma=86400"
  }
}