{
  "source": {
    "name": "WIRED",
    "url": "https://www.wired.com",
    "language": "English",
    "group": "News & Blogs/English"
  },
  "requested_url": "https://www.wired.com",
  "final_url": "https://www.wired.com/",
  "status_code": 200,
  "fetched_at": "2025-09-13T11:18:42.838318Z",
  "headers": {
    "Content-Type": "text/html; charset=utf-8",
    "Transfer-Encoding": "chunked",
    "Connection": "keep-alive",
    "Server": "CloudFront",
    "Date": "Sat, 13 Sep 2025 11:15:49 GMT",
    "Modified-At": "1757722476",
    "Cache-Control": "stale-while-revalidate=60, stale-if-error=86400, s-maxage=900",
    "Back-Lae-Origin-Response-Start": "1757762149152",
    "X-Organization-Slug": "wired",
    "X-Content-Type-Options": "nosniff",
    "X-Ua-Device": "desktop",
    "Via": "1.1 3bc52f7e0135d4a9f867e6a9ee5796b0.cloudfront.net (CloudFront), 1.1 2c75ace4dd204c0629bda3cfca0f640c.cloudfront.net (CloudFront)",
    "Content-Encoding": "gzip",
    "Vary": "accept-encoding",
    "Alt-Svc": "h3=\":443\"; ma=86400",
    "Age": "182",
    "Set-Cookie": "CN_geo_country_code=NG; Expires=Thu, 12 Mar 2026 11:18:51 GMT; path=/; Domain=.wired.com;  Secure; SameSite=None;, CN_segments=co.w2537; Expires=Thu, 12 Mar 2026 11:18:51 GMT; Domain=.wired.com; path=/;, CN_xid=4863ebcd-01dd-4236-bb73-da36d5afb07c; Expires=Thu, 12 Mar 2026 11:18:51 GMT; Domain=.wired.com; path=/; Secure; SameSite=None;, CN_xid_refresh=4863ebcd-01dd-4236-bb73-da36d5afb07c; Expires=Sun, 13 Sep 2026 11:18:51 GMT; Domain=.wired.com; path=/; Secure; httponly; SameSite=None;, xid1=1; Expires=Sat, 13 Sep 2025 11:19:06 GMT; Domain=.wired.com; path=/;",
    "X-Amz-Cf-Pop": "LHR50-C1, LOS50-P2",
    "X-Cache": "Hit from cloudfront",
    "X-Amz-Cf-Id": "AI_xzwCNbu6-Enw-r0fvGJZYijIzzY3b1RPlAuPr0RQIiOOGqklQ7Q=="
  }
}